wims_api_utils/__init__.py
wims_api_utils/exceptions/__init__.py
wims_api_utils/schemas/__init__.py
wims_api_utils/schemas/formio_roles.py
wims_api_utils/services/__init__.py
wims_api_utils/services/external/__init__.py
wims_api_utils/services/external/formio.py
wims_api_utils/utils/__init__.py
wims_api_utils/utils/auth.py
wims_api_utils/utils/caching.py
wims_api_utils/utils/constants.py
wims_api_utils/utils/enums.py
wims_api_utils/utils/format.py
wims_api_utils/utils/logging.py
wims_api_utils/utils/pdf.py
wims_api_utils/utils/profiler.py
wims_api_utils/utils/roles.py
wims_api_utils/utils/startup.py
wims_api_utils/utils/user_context.py
wims_api_utils/utils/util.py
wims_api_utils/utils/translations/__init__.py
wims_api_utils/utils/translations/translations.py
wims_api_utils-1.0.0.dist-info/METADATA
wims_api_utils-1.0.0.dist-info/WHEEL
wims_api_utils-1.0.0.dist-info/top_level.txt
wims_api_utils-1.0.0.dist-info/RECORD
