Metadata-Version: 2.1
Name: wims-api-utils
Version: 1.0.0
Summary: WIMS api related libraries.
Home-page: https://github.com/katxeus/wims_api_utils
Author: JK
Requires-Dist: gunicorn
Requires-Dist: Flask
Requires-Dist: Flask-Caching
Requires-Dist: Flask-Migrate
Requires-Dist: Flask-Moment
Requires-Dist: Flask-SQLAlchemy
Requires-Dist: flask-restx
Requires-Dist: flask-marshmallow
Requires-Dist: flask-jwt-oidc
Requires-Dist: python-dotenv
Requires-Dist: psycopg2-binary
Requires-Dist: marshmallow-sqlalchemy
Requires-Dist: requests
Requires-Dist: Werkzeug
Requires-Dist: sqlalchemy-utils
Requires-Dist: markupsafe
Requires-Dist: PyJWT
Requires-Dist: selenium
Requires-Dist: selenium-wire
